repoconf/__init__.py
repoconf/py.typed
repoconf/cli/__init__.py
repoconf/core/__init__.py
repoconf-0.0.0.dev0.dist-info/licenses/LICENSE
repoconf-0.0.0.dev0.dist-info/METADATA
repoconf-0.0.0.dev0.dist-info/WHEEL
repoconf-0.0.0.dev0.dist-info/top_level.txt
repoconf-0.0.0.dev0.dist-info/RECORD
