Metadata-Version: 2.4
Name: repoconf
Version: 0.0.0.dev0
Summary: Centrally configure your decentralised git repo
Author-email: Suhas Krishna Srivastava <suhas.srivastava@vaastav.tech>
Maintainer-email: Suhas Krishna Srivastava <suhas.srivastava@vaastav.tech>
License-Expression: Apache-2.0
Project-URL: homepage, https://github.com/Vaastav-Technologies/py-repoconf
Project-URL: source, https://github.com/Vaastav-Technologies/py-repoconf
Project-URL: issues, https://github.com/Vaastav-Technologies/py-repoconf/issues
Keywords: config,version-control,configuration,git,vcs,library,version control,centralized,central
Classifier: Development Status :: 1 - Planning
Classifier: Environment :: Console
Classifier: Intended Audience :: Developers
Classifier: Intended Audience :: Education
Classifier: Intended Audience :: End Users/Desktop
Classifier: Intended Audience :: System Administrators
Classifier: Topic :: Education
Classifier: Topic :: Software Development
Classifier: Topic :: Software Development :: Version Control
Classifier: Topic :: Software Development :: Version Control :: Git
Classifier: Topic :: Security
Classifier: Topic :: Security :: Cryptography
Classifier: Operating System :: OS Independent
Classifier: Programming Language :: Python :: 3.12
Classifier: Programming Language :: Python :: 3.13
Classifier: Programming Language :: Python :: 3 :: Only
Classifier: Typing :: Typed
Requires-Python: >=3.12
License-File: LICENSE
Requires-Dist: logician>=0.0.0.dev6
Requires-Dist: gitbolt>=0.0.0.dev10
Requires-Dist: vt-commons>=0.0.1.dev4
Requires-Dist: vt-err-hndlr>=0.0.0.dev3
Dynamic: license-file
